{"1456404305494249481":{"created_at":"Thu Nov 04 23:33:39 +0000 2021","id_str":"1456404305494249481","text":"These Parents Built a School App. Then the City Called the Cops https://t.co/UcGbKk9Ewx","users":[],"urls":["https://www.wired.com/story/sweden-stockholm-school-app-open-source/"],"engage":1,"areas":["Open Source"],"people":["Kin Lane"]},"1456028796910452736":{"created_at":"Wed Nov 03 22:41:31 +0000 2021","id_str":"1456028796910452736","text":"@chris_trag @StripeDev Thank you for joining me! I love the \"old dog\" vibe that exists between us when it comes to evangelism and advocacy. Always game to swap stores and look forward to coming down to Austin sometime!","users":["chris_trag","StripeDev"],"urls":[],"engage":1,"people":["Kin Lane"]},"1455995290893225986":{"created_at":"Wed Nov 03 20:28:23 +0000 2021","id_str":"1455995290893225986","text":"@DoerrfeldBill @getpostman Understood. Definitely part of the discussion moving forward. I so get it. Spent years in your shoes railing against the motivations behind content in the space -- event built tooling to address. Then gave up. :-) Keep railing my friend. https://t.co/ISgbavdwEb","users":["DoerrfeldBill","getpostman"],"urls":[],"engage":1,"components":["Support"],"people":["Kin Lane"]},"1455306386326179842":{"created_at":"Mon Nov 01 22:50:55 +0000 2021","id_str":"1455306386326179842","text":"I invented a new word today -- untigration. You know like API untigration, the act of removing the integrations that exist between our systems.","users":[],"urls":[],"engage":1,"people":["Kin Lane"]},"1453825744308559872":{"created_at":"Thu Oct 28 20:47:22 +0000 2021","id_str":"1453825744308559872","text":"Hey @a85, a good API-First definition: When your API project surpasses your core business as the driver of revenue. https://t.co/e0jKQ8Jvaw","users":["a85"],"urls":["https://twitter.com/Techmeme/status/1453818341995409423"],"people":["Kin Lane"],"engage":1,"areas":["API-First"]},"1445871263201726468":{"created_at":"Wed Oct 06 21:59:06 +0000 2021","id_str":"1445871263201726468","text":"I caught a glimpse of the future with APIs in my Breaking Changes conversation with @sramji today - https://t.co/ZAe4beaOUZ","users":["sramji"],"urls":["https://www.postman.com/events/breaking-changes/the-new-api-stack-for-modern-data-apps/"],"engage":1,"components":["Breaking Changes"],"people":["Kin Lane"],"areas":["Data"]}}